pyqcolored/__init__.py
pyqcolored/test.py
pyqcolored-1.0.dist-info/METADATA
pyqcolored-1.0.dist-info/WHEEL
pyqcolored-1.0.dist-info/top_level.txt
pyqcolored-1.0.dist-info/RECORD
