Metadata-Version: 2.1
Name: pyqcolored
Version: 1.0
Summary: A command line tool for colors
Author-email: smithsha@gmail.com
License: Eclipse Public License 2.0
